ansible_anonymizer/__init__.py
ansible_anonymizer/anonymizer.py
ansible_anonymizer/cli.py
ansible_anonymizer/field_checks.py
ansible_anonymizer/jinja2.py
ansible_anonymizer/node.py
ansible_anonymizer/parser.py
ansible_anonymizer/parser_multi_lines.py
ansible_anonymizer-1.5.0.dist-info/LICENSE
ansible_anonymizer-1.5.0.dist-info/METADATA
ansible_anonymizer-1.5.0.dist-info/WHEEL
ansible_anonymizer-1.5.0.dist-info/entry_points.txt
ansible_anonymizer-1.5.0.dist-info/top_level.txt
ansible_anonymizer-1.5.0.dist-info/RECORD
