Metadata-Version: 2.1
Name: ansible-anonymizer
Version: 1.5.0
Summary: Ansible Anonymizer
Author-email: Gonéri Le Bouder <goneri@lebouder.net>
Project-URL: Homepage, https://github.com/ansible/anonymizer
Keywords: pii,anonymize
Classifier: License :: OSI Approved :: Apache Software License
Classifier: Programming Language :: Python :: 3
Requires-Python: >=3.9
License-File: LICENSE
Provides-Extra: test
Requires-Dist: tox ; extra == 'test'
